ib_web_api/__init__.py
ib_web_api/api_client.py
ib_web_api/configuration.py
ib_web_api/rest.py
ib_web_api/api/__init__.py
ib_web_api/api/account_api.py
ib_web_api/api/alert_api.py
ib_web_api/api/ccp__beta_api.py
ib_web_api/api/contract_api.py
ib_web_api/api/fyi_api.py
ib_web_api/api/ib_cust_api.py
ib_web_api/api/market_data_api.py
ib_web_api/api/order_api.py
ib_web_api/api/pn_l_api.py
ib_web_api/api/portfolio_analyst_api.py
ib_web_api/api/portfolio_api.py
ib_web_api/api/scanner_api.py
ib_web_api/api/session_api.py
ib_web_api/api/streaming_api.py
ib_web_api/api/trades_api.py
ib_web_api/models/__init__.py
ib_web_api/models/account.py
ib_web_api/models/account_id_orders_body.py
ib_web_api/models/account_orders_body.py
ib_web_api/models/account_parent.py
ib_web_api/models/accounts.py
ib_web_api/models/alert_activate_body.py
ib_web_api/models/alert_request.py
ib_web_api/models/alert_response.py
ib_web_api/models/alertrequest_conditions.py
ib_web_api/models/alertresponse_conditions.py
ib_web_api/models/allocation.py
ib_web_api/models/allocation_inner.py
ib_web_api/models/auth_init_body.py
ib_web_api/models/auth_response_body.py
ib_web_api/models/auth_status.py
ib_web_api/models/calendar_request.py
ib_web_api/models/calendar_request_date.py
ib_web_api/models/calendar_request_filters.py
ib_web_api/models/contract.py
ib_web_api/models/contract_rules.py
ib_web_api/models/contract_rules_body.py
ib_web_api/models/deliveryoptions_device_body.py
ib_web_api/models/events.py
ib_web_api/models/events_inner.py
ib_web_api/models/futures.py
ib_web_api/models/futures_inner.py
ib_web_api/models/history_data.py
ib_web_api/models/history_result.py
ib_web_api/models/historydata_data.py
ib_web_api/models/historyresult_bars.py
ib_web_api/models/historyresult_bars_data.py
ib_web_api/models/hmds_scanner_body.py
ib_web_api/models/hmdsscanner_filters.py
ib_web_api/models/ibcustentityinfo_address.py
ib_web_api/models/ibcustentityinfo_entities.py
ib_web_api/models/ibcustentityinfo_name.py
ib_web_api-202303101433.dist-info/METADATA
ib_web_api-202303101433.dist-info/WHEEL
ib_web_api-202303101433.dist-info/top_level.txt
ib_web_api-202303101433.dist-info/RECORD
